worldcoinapi.py
worldcoinapi-1.0.2.dist-info/WHEEL
worldcoinapi-1.0.2.dist-info/METADATA
worldcoinapi-1.0.2.dist-info/RECORD
